py_stay-0.2.1.dist-info/licenses/AUTHORS.rst
py_stay-0.2.1.dist-info/licenses/LICENSE
stay/__init__.py
stay/py.typed
stay/stay.py
py_stay-0.2.1.dist-info/METADATA
py_stay-0.2.1.dist-info/WHEEL
py_stay-0.2.1.dist-info/top_level.txt
py_stay-0.2.1.dist-info/RECORD
