Metadata-Version: 2.4
Name: py-stay
Version: 0.2.1
Summary: Simple Typed Argparse, Yes
Author-email: Daniel Kramer <drkspace@gmail.com>
Maintainer-email: Daniel Kramer <drkspace@gmail.com>
License: MIT license
Project-URL: bugs, https://github.com/drkspace/stay/issues
Project-URL: changelog, https://github.com/drkspace/stay/blob/master/changelog.md
Project-URL: homepage, https://github.com/drkspace/stay
Classifier: Development Status :: 4 - Beta
Classifier: Intended Audience :: Developers
Classifier: Programming Language :: Python :: 3
Classifier: Programming Language :: Python :: 3.8
Classifier: Programming Language :: Python :: 3.9
Classifier: Programming Language :: Python :: 3.10
Classifier: Programming Language :: Python :: 3.11
Classifier: Programming Language :: Python :: 3.12
Classifier: Programming Language :: Python :: 3.13
Requires-Python: >=3.8
License-File: LICENSE
License-File: AUTHORS.rst
Requires-Dist: typing_extensions
Provides-Extra: dev
Requires-Dist: coverage; extra == "dev"
Requires-Dist: mypy; extra == "dev"
Requires-Dist: pytest; extra == "dev"
Requires-Dist: ruff; extra == "dev"
Requires-Dist: bump-my-version; extra == "dev"
Requires-Dist: pytest-cov; extra == "dev"
Requires-Dist: build; extra == "dev"
Requires-Dist: pytest-random-order; extra == "dev"
Requires-Dist: pre-commit; extra == "dev"
Dynamic: license-file
